obynutils/__init__.py
obynutils/cache_manager.py
obynutils/change_presence.py
obynutils/config_manager.py
obynutils/gatekeeper.py
obynutils/multi_convter.py
obynutils/obyn_embed.py
obynutils/setup_database.py
obynutils-0.1.0.dist-info/METADATA
obynutils-0.1.0.dist-info/WHEEL
obynutils-0.1.0.dist-info/top_level.txt
obynutils-0.1.0.dist-info/RECORD
